{
  "Gl 406": "dM6",
  "Gl 65A": "M5.5V",
  "Gl 905": "M5.0V",
  "Gl 866A": "M5V",
  "GJ 1111": "M6.5Ve",
  "GJ 1061": "M5.5V",
  "Gl 83.1": "M4.5V",
  "GJ 3622": "M6.5V",
  "GJ 1245A": "M5.5Ve",
  "GJ 3618": "M5.5V",
  "GJ 1002": "M5.5V",
  "GJ 1116A": "M8Ve",
  "GJ 3323": "M4.0Ve",
  "Gl 169.1A": "M4.0V",
  "Gl 754": "M4.5V",
  "GJ 1221": "DQ9P",
  "Gl 223.2": "DZ11",
  "GJ 1156": "M4.5Ve",
  "GJ 1128": "M4.0V",
  "GJ 3737": "M4.5V",
  "Gl 299": "M4.5V",
  "GJ 3522": "M3.5V",
  "GJ 3877": "M7.0Ve",
  "GJ 1068": "M4.5V",
  "GJ 1286": "M5.0Ve",
  "GJ 4274": "M4.5Ve",
  "Gl 791.2": "M4.5V",
  "GJ 4053": "M4.5Ve",
  "GJ 4248": "M3.5V",
  "GJ 2005": "M5.5/6Ve+M8.5Ve+M9/9.5V",
  "GJ 3378": "M4.0V",
  "GJ 1093": "M5.0Ve",
  "GJ 1224": "M4.0Ve",
  "GJ 1151": "M4.5V",
  "GJ 1154A": "M3.5V",
  "Gl 300": "DA8P",
  "GJ 1087": "DA9.0",
  "Gl 293": "M3V",
  "Gl 747A": "DAP5.8",
  "Gl 915": "DC9",
  "Gl 518": "M4.0V",
  "GJ 1227": "M4.5Ve",
  "GJ 1289": "M4V",
  "Gl 232": "M4.5V",
  "GJ 3454": "DA5.5",
  "Gl 318": "DZ13",
  "GJ 1276": "M4.5Ve",
  "Gl 493.1": "M4.5V",
  "GJ 3517": "M9Ve",
  "GJ 1207": "dM4",
  "GJ 2066": "M2.0V",
  "GJ 3421": "M5.0V",
  "GJ 3146": "M5.0Ve",
  "GJ 2012": "DQ9",
  "GJ 4247": "M3.5Ve",
  "Gl 283A": "DZQA6",
  "GJ 3128": "M5.5V",
  "GJ 1103A": "M4.5V",
  "GJ 3817": "M3.5Ve",
  "GJ 3306": "DQ8",
  "GJ 3512": "dM5.5",
  "GJ 1123": "M4.5V",
  "GJ 3380": "M5.0V",
  "GJ 1256": "M4.5V",
  "GJ 3571": "M4.0Ve",
  "GJ 1253": "dM5.0",
  "GJ 3253": "M5V",
  "GJ 3112": "DA8.1",
  "GJ 1138": "M5V",
  "GJ 1028": "dM5.0",
  "Gl 51": "M5V",
  "GJ 3988": "M5.0V",
  "GJ 1065": "M3V",
  "GJ 1230A": "M4.5V",
  "GJ 3855": "M6.5V",
  "Gl 102": "M3.5Ve",
  "Gl 609": "M4V",
  "GJ 1134": "M4.0V",
  "Gl 590": "M4.5V",
  "GJ 1119": "M4.5Ve",
  "GJ 3326": "M5V",
  "GJ 1265": "dM4.5",
  "GJ 3049": "M3V",
  "GJ 1083A": "DCP7",
  "Gl 339.1": "M4V",
  "GJ 1232": "M7V",
  "GJ 3147": "M4.5V",
  "GJ 1277": "M5V",
  "GJ 3976": "M4.5Ve",
  "GJ 3119": "M4.0Ve",
  "GJ 1235": "dM4.5",
  "GJ 3426": "M4V",
  "GJ 1236": "M6V",
  "GJ 1238": "M4V",
  "Gl 766A": "M2.5V",
  "GJ 4154": "M4.5V",
  "GJ 3820": "DAZ9",
  "GJ 1050": "M2.5V",
  "GJ 1004": "DA7.6",
  "Gl 170": "M5V",
  "GJ 4281": "M6.5V",
  "GJ 4071": "M5V",
  "GJ 3849": "M9Ve",
  "Gl 145": "M2.5V",
  "GJ 1129": "M3.5Ve",
  "Gl 836.5": "DQ6",
  "Gl 852A": "M4V",
  "GJ 3069": "dM5.5",
  "GJ 1088": "M3.5V",
  "Gl 585": "dM5.0",
  "GJ 1086": "DQ8P",
  "GJ 3959": "M6V",
  "Gl 275.2A": "M4V",
  "GJ 3967": "M5V",
  "Gl 568A": "M6V+M5V",
  "GJ 3417": "M5.5V",
  "GJ 1187": "sdM3.0",
  "GJ 3189": "M4.5V",
  "GJ 3668": "DA6.4",
  "Gl 772": "M2V",
  "GJ 3333": "M3V",
  "GJ 2112A": "M3V",
  "GJ 1097": "M4V",
  "Gl 46": "M4.5Ve",
  "Gl 810A": "DC7",
  "GJ 3125": "M5V",
  "GJ 4288A": "M3V",
  "GJ 1234": "M3V",
  "GJ 1179A": "M4.5V",
  "GJ 3356": "M4.0Ve",
  "GJ 4350": "M4V",
  "GJ 1243": "M4V",
  "Gl 277A": "M4V",
  "GJ 4065": "M3.5V",
  "GJ 3992": "M5V",
  "GJ 3266": "M4V",
  "GJ 4207": "M4V",
  "GJ 1053": "M5V",
  "Gl 12": "dM5.0",
  "GJ 4198": "M5.5V",
  "GJ 1210": "dM3.5",
  "GJ 1223": "DC",
  "GJ 3497": "M7V",
  "GJ 3526": "M4.0V",
  "Gl 85": "M1.5V",
  "GJ 1001": "M4V",
  "Gl 359": "dM5.0",
  "GJ 1215": "M5V",
  "GJ 1025": "M4.0V",
  "GJ 1263": "dM4.0",
  "Gl 732A": "M3.5V",
  "GJ 4098": "M3V",
  "GJ 4102": "M3.5V",
  "GJ 4069": "dM5.0",
  "GJ 3250": "M5V",
  "GJ 1029": "M5V",
  "GJ 1194A": "M3V",
  "GJ 1055": "M5V",
  "GJ 4078": "M3.5V",
  "GJ 1132": "M3.5V",
  "Gl 64": "DA+D1",
  "GJ 1072": "M5V",
  "GJ 3612": "M4V",
  "GJ 4004": "M3.5V",
  "GJ 3708A": "M4V",
  "GJ 3666": "M2Vk",
  "Gl 91": "M4V",
  "GJ 3009": "M4V",
  "GJ 1031": "M5V",
  "GJ 4169": "M4.8V",
  "GJ 1167A": "M5V",
  "Gl 774A": "M4V",
  "GJ 1220": "M4.5V",
  "GJ 1251": "DAP4.5",
  "Gl 742": "M2.5V",
  "GJ 3722": "M5V",
  "GJ 1288": "M1V",
  "Gl 525": "dM3.5",
  "Gl 843": "M5.5V",
  "GJ 2045": "M5.0V",
  "GJ 1101": "M4V",
  "GJ 1158": "M5V",
  "GJ 3467": "M1V",
  "Gl 835": "M4V",
  "GJ 3586": "M2.5V",
  "Gl 63": "M3Ve",
  "Gl 865": "M4.0V",
  "Gl 164": "M4V",
  "Gl 403": "M4.0Ve",
  "GJ 3423": "DC10",
  "GJ 4055": "M3.5V",
  "Gl 195A": "M2.5V",
  "GJ 3647": "M3.5V",
  "GJ 3843": "dM4.0",
  "GJ 1012": "dM4.0",
  "GJ 3148A": "M3.5V",
  "GJ 3775": "M3.5V",
  "GJ 2070": "M5V",
  "GJ 4239": "M3.7V",
  "GJ 3036": "M5V",
  "GJ 1073": "M4.5V",
  "GJ 3442": "M6.0V",
  "Gl 316.1": "M5V",
  "GJ 3296": "M3V",
  "GJ 3777": "DA10",
  "GJ 4054": "M4V",
  "GJ 3779": "M1.5V",
  "GJ 4122": "dM5.0",
  "GJ 4279": "M3.5V",
  "GJ 3500": "M3.5V",
  "Gl 545": "M5V",
  "GJ 1182": "dM5.5",
  "GJ 3631": "M6V",
  "GJ 3181": "dM4.0",
  "Gl 592": "M3.5V",
  "GJ 3654": "dM5.0",
  "GJ 3780": "M4V",
  "GJ 1270": "M3.5V",
  "GJ 1013": "M6V",
  "GJ 3762": "DQ10P",
  "GJ 3614": "M3V",
  "GJ 3286": "M7V",
  "GJ 3971": "M3V",
  "GJ 3625": "M8.5V",
  "GJ 3655": "M7.5Ve",
  "GJ 4073": "M5V",
  "GJ 1014": "M5V",
  "GJ 3520": "M1.5V",
  "Gl 130": "M5V",
  "GJ 1035": "M4V",
  "GJ 1092": "M3.5V",
  "GJ 3740": "DAZ7.6",
  "GJ 3965": "M5V",
  "GJ 3270": "M4.5V",
  "GJ 1214": "M8.0V",
  "GJ 3252": "DA6.8",
  "Gl 427": "M5V",
  "GJ 1059": "M4.5V",
  "GJ 3463": "M3.5V",
  "Gl 712": "M4V",
  "GJ 3001": "DC",
  "GJ 3141": "M2.5V",
  "GJ 2095": "DA4.2",
  "Gl 630.1A": "M4.5V",
  "GJ 3637": "M5V",
  "GJ 3693": "M8V",
  "Gl 891": "M2V",
  "GJ 3208": "M6V",
  "GJ 3873": "M3.5V",
  "Gl 589A": "M2.5V",
  "GJ 1171": "M5V",
  "GJ 3053": "M4.5V",
  "GJ 3060A": "M3.5V",
  "GJ 9780": "M4V",
  "GJ 4026": "M3.0V",
  "GJ 3885": "M3V",
  "GJ 3382": "dM4.0",
  "GJ 3357": "M5V",
  "GJ 3550": "M4V",
  "GJ 1204": "M3.5V",
  "Gl 317": "M2.5+V",
  "GJ 1046": "M4.5V",
  "GJ 3093A": "M4V",
  "GJ 3894": "M3V",
  "GJ 3142": "M5V",
  "GJ 1147": "M4V",
  "GJ 1096": "M4V",
  "Gl 398": "M3V",
  "GJ 3692": "M3.5V",
  "GJ 1081": "M4.5V",
  "GJ 3350": "M4V",
  "GJ 3533": "DA6.6",
  "GJ 2092": "M5V",
  "Gl 326A": "M3.0V",
  "Gl 792": "M3.5V",
  "GJ 4312": "M4V",
  "GJ 3960": "M4V",
  "GJ 1169": "M0V",
  "GJ 3704": "M5V",
  "GJ 3077A": "M2.5V",
  "GJ 3480": "M4V",
  "GJ 3542": "M2.5V",
  "GJ 4129": "M2.5V",
  "GJ 3518": "M4.5V",
  "GJ 1099": "M3V",
  "GJ 4216": "dM4.0",
  "GJ 4202": "M4V",
  "GJ 1037": "DC6",
  "GJ 3691": "dM4.5",
  "GJ 4109": "M3.5V",
  "GJ 3770": "DC",
  "GJ 1292": "M3V",
  "GJ 4283": "M3.0V",
  "Gl 231.3": "M3V",
  "GJ 1202": "M4V",
  "GJ 4225": "M2V",
  "GJ 3759": "M1V",
  "GJ 4203A": "M4V",
  "GJ 3812": "M4.0Ve",
  "GJ 3919": "M3.0V",
  "GJ 3918": "dM4.5",
  "GJ 3120": "M2V",
  "GJ 3811": "DZA9",
  "GJ 3223": "M2.5V",
  "Gl 633": "M4V",
  "GJ 3503": "M3.5V",
  "GJ 1200": "dM4.0",
  "GJ 4367": "M2.5V",
  "Gl 808": "DQ7P",
  "GJ 1228": "M2.5V",
  "GJ 3563": "M3.5V",
  "GJ 3198": "dM2.5",
  "GJ 4077": "M4.0Ve",
  "GJ 4214A": "M3.5Ve",
  "GJ 3136": "dM4.5",
  "GJ 3221": "M7V",
  "GJ 4219": "M4V",
  "GJ 4386": "DAZ6.9",
  "GJ 1131": "M5V",
  "GJ 1042": "M4.0Ve",
  "GJ 3076": "M3.5V",
  "GJ 3966": "M3.5V",
  "GJ 1174": "DA10",
  "GJ 3303": "dM3.5",
  "GJ 4133": "M4.5",
  "Gl 204.2": "M2.5V",
  "GJ 3943": "dM4.0",
  "GJ 4056": "M2.5V",
  "GJ 3893": "M3.5V",
  "GJ 1036": "M2.5V",
  "Gl 94": "sdM3.5",
  "GJ 4143": "DA4.1",
  "Gl 455": "M3V",
  "GJ 1183A": "M4.5V",
  "GJ 3937": "M4.5V",
  "GJ 3366": "M4.5V",
  "GJ 3521": "M3.5V",
  "GJ 4165": "DA3.4",
  "GJ 3553": "M4V",
  "GJ 3514": "M4.5V",
  "GJ 3398": "M4.5V",
  "GJ 3787": "M3.5V",
  "GJ 3479": "M3.0V",
  "GJ 4257": "dM4.5",
  "GJ 4036": "M3V",
  "GJ 3981": "M4.0Ve",
  "GJ 1007": "M4V",
  "GJ 2021": "M4V",
  "Gl 878": "M3V",
  "GJ 1273": "DA4.7",
  "GJ 4044": "M4.0V",
  "GJ 1211": "DZ7",
  "GJ 3582": "dM4.5",
  "Gl 912": "M2.5Vk",
  "GJ 4267": "M3V",
  "GJ 3045": "M3.0V",
  "GJ 4105": "M2V",
  "GJ 4316": "M3V",
  "GJ 1216": "M4V",
  "GJ 3823": "sdM2",
  "GJ 3659": "M3V",
  "GJ 3796": "M2V",
  "GJ 3225": "dM5.0",
  "GJ 3410": "DA7.0",
  "GJ 3010": "M5V",
  "GJ 1102A": "DC9",
  "GJ 3975": "M3.5V",
  "GJ 3757": "M5V",
  "GJ 4228": "M4V",
  "GJ 3809A": "M1.5",
  "GJ 3671": "M0V",
  "GJ 1024": "M4V",
  "GJ 3672": "M4.5V",
  "GJ 1185": "M2V",
  "GJ 3858": "dM4.0",
  "GJ 1241": "DA4.0",
  "GJ 3573": "M4V",
  "GJ 4112": "M4V",
  "GJ 3132": "M4V",
  "GJ 3913": "M3.5V",
  "GJ 3990": "dM5.0",
  "Gl 165A": "M3.0Ve",
  "GJ 3923": "M3.5V",
  "GJ 1219": "M4V",
  "GJ 4297": "M3V",
  "GJ 3652": "M3.5V",
  "GJ 3016": "DC8H",
  "Gl 741": "M4V",
  "GJ 4064": "M2.0V",
  "GJ 3259": "DC9",
  "GJ 3098": "M1.5Vk:",
  "GJ 4355": "DA4.5",
  "GJ 3766": "dM6.5",
  "GJ 1162": "M3.5V",
  "GJ 3878A": "M6V",
  "GJ 3600A": "M5V",
  "GJ 3153": "M4V",
  "GJ 3018A": "M3V",
  "GJ 3552": "M3.0V",
  "GJ 4074": "M4.5V",
  "GJ 3685A": "M4V",
  "GJ 1118": "DQ8",
  "GJ 3213": "M5.0V",
  "GJ 3907": "M4V",
  "GJ 3027": "M1.5Vk:",
  "Gl 151": "M2.5V",
  "GJ 1225": "M3V",
  "GJ 3702": "M4.0Ve",
  "GJ 3973": "M5V",
  "Gl 121.1": "DA7.8",
  "GJ 3758": "M3.5V",
  "GJ 3898": "dM4.5",
  "GJ 1231": "DA9",
  "GJ 2135": "M3.5V",
  "GJ 2133": "M3.5Ve",
  "GJ 3134": "M5V",
  "GJ 4166": "M3.5V",
  "GJ 3632": "DQ",
  "GJ 3572": "M3.5V",
  "GJ 4385": "M3.5",
  "GJ 3406A": "M1.5V",
  "GJ 3081": "M4V",
  "GJ 3483": "M3.5V",
  "GJ 3496": "M2.5V",
  "GJ 3545": "M2+V",
  "GJ 3567": "M3.0V",
  "GJ 4132": "DAH9",
  "GJ 2077": "DC7",
  "GJ 4242A": "M3V",
  "GJ 3964": "M4V",
  "GJ 3727A": "M6V",
  "Gl 836": "M4V",
  "GJ 3169A": "M5V",
  "GJ 3311": "M5V",
  "GJ 4361": "dM4.0",
  "GJ 1186": "dM5.0",
  "GJ 3033": "M2.0V",
  "GJ 3772": "M2.5V",
  "GJ 4089": "DA3.0",
  "GJ 1022": "M3.5V",
  "Gl 524": "M3.0Ve",
  "GJ 2149": "M2.5V",
  "GJ 3524": "dM5.0",
  "GJ 3096": "DC10",
  "Gl 769": "K9V",
  "GJ 3984": "M3.5V",
  "GJ 3420": "M4V",
  "GJ 1016": "M4V",
  "GJ 4083": "DAP5.3",
  "GJ 3963": "M3.5V",
  "GJ 4185A": "M5V",
  "GJ 4007": "M2.5V",
  "GJ 3814": "M4V",
  "GJ 3051": "M5V",
  "GJ 4292": "DA3.3",
  "GJ 3139": "K6V",
  "GJ 3393": "M3.5V",
  "GJ 4378A": "DA8.6",
  "GJ 3373A": "DA11P",
  "GJ 4294": "DA8.1",
  "Gl 755.1": "M3.7V",
  "Gl 910": "dM4.0",
  "GJ 1146": "M5V",
  "GJ 3710": "M3.5V",
  "GJ 1098": "M3.5V",
  "GJ 1275": "DAEH6.5",
  "GJ 3174": "M4.5V",
  "Gl 101": "M3.4V",
  "GJ 1070": "M2.5V",
  "GJ 3821": "M2.5V",
  "GJ 4197": "M4V",
  "GJ 4354": "dM3.5",
  "GJ 4108": "M4.5V",
  "GJ 4136": "M3V",
  "GJ 2034": "DA7.8",
  "GJ 3568": "M4V",
  "GJ 3288": "DC9",
  "GJ 4002": "M3V",
  "GJ 3337": "dM4.0",
  "GJ 9732": "M1.5V",
  "GJ 3562": "dM4.0",
  "GJ 3731A": "dM4.5",
  "GJ 4135": "M3.5V",
  "GJ 4276": "M2V",
  "GJ 4104": "M4.5V",
  "GJ 4272": "M3.5V",
  "GJ 4030": "M2.5V",
  "GJ 1281": "M3V",
  "GJ 4023": "M2.5V",
  "GJ 3840": "M3V",
  "GJ 3599": "M3V",
  "GJ 4045": "M5V",
  "GJ 3636": "M2.0V",
  "GJ 3414": "M2.5V",
  "GJ 3349": "dM5.0",
  "GJ 4218": "M4V",
  "GJ 1034": "DA7.6",
  "GJ 3339": "DA7.4",
  "GJ 1052": "M2V",
  "GJ 3968": "M4V",
  "GJ 3756": "M4V",
  "GJ 3900": "dM4.0",
  "GJ 3265": "M4.5V",
  "GJ 1198": "M1.5V",
  "Gl 874": "M4.5V",
  "GJ 1250": "M5.5V",
  "GJ 4037": "M3.5V",
  "GJ 3137": "M1.5+V",
  "GJ 2033": "M4V",
  "GJ 3696": "M4.5V",
  "GJ 4137": "dM4.0",
  "GJ 3751": "M4V",
  "GJ 4151": "M1V",
  "GJ 4170": "M6V",
  "GJ 3724": "M4V",
  "GJ 1045": "dM4.0",
  "GJ 3165": "M3.5V",
  "GJ 4067": "M3.5V",
  "GJ 1168": "DA5.9",
  "GJ 4201": "M4.0V",
  "GJ 3485": "M4V",
  "GJ 1018": "M2V",
  "GJ 3164": "M3V",
  "GJ 3353A": "M3.0V",
  "Gl 333.2A": "M3.0V",
  "GJ 4240": "M4.5V",
  "GJ 4284": "M2.0V",
  "Gl 351.1": "DA3.1",
  "Gl 828.5": "M5V",
  "GJ 3635": "M3V",
  "Gl 226.1": "DA5.4",
  "GJ 1199": "M1V",
  "GJ 9784": "dM4.0",
  "GJ 3983": "M4.5V",
  "GJ 3035": "M3V",
  "GJ 3159": "M4V",
  "GJ 3368": "M2.5V",
  "GJ 3249": "DA6.8",
  "GJ 1112": "M4V",
  "GJ 3579": "M2V",
  "GJ 3430A": "DA7.1",
  "GJ 4262": "M3.5Ve",
  "GJ 3064": "M2.0V",
  "GJ 1163": "dM4.0",
  "GJ 3204": "M3V",
  "GJ 3047": "M3.5V",
  "GJ 1197": "dM4.0",
  "GJ 3207": "M4.5V",
  "GJ 3413": "dM4.0",
  "GJ 4335": "M3.5V",
  "GJ 3068": "M3.6V",
  "GJ 3626": "M3.5V",
  "GJ 3150": "M4V",
  "GJ 4271": "M2.5V/M3V",
  "GJ 1033": "M3.5V",
  "GJ 2121": "M4V",
  "GJ 4032": "M3.5V",
  "GJ 1193": "M4.0V",
  "GJ 4175": "M6V",
  "GJ 3730": "M0V",
  "GJ 3158": "M2.5V",
  "GJ 3328": "M3.8V",
  "GJ 3287": "M3.0V",
  "GJ 1047A": "M2.5V",
  "GJ 3795": "M3.5V",
  "GJ 2003": "M1+Vk:",
  "GJ 1015A": "M4V",
  "Gl 157.1": "M4V",
  "GJ 3941": "M3.0V",
  "Gl 784.2A": "M3.5V",
  "GJ 3927": "M5V",
  "GJ 1060A": "DA5.4",
  "GJ 3738": "M2.5Ve",
  "GJ 3172": "M5V",
  "GJ 3778": "M2.0V",
  "GJ 3537": "M4Ve",
  "GJ 4300": "M2.5V",
  "GJ 4162": "M3.5V",
  "GJ 1117": "DQ6",
  "GJ 1242": "M2V",
  "GJ 4260": "M3.0V",
  "GJ 3739": "M4V",
  "GJ 3316": "dM3.0",
  "GJ 3365": "M4.0V",
  "GJ 3986": "M3.0V",
  "GJ 3623": "M3V",
  "GJ 3911": "dM4.0",
  "GJ 3190": "dM4.0",
  "GJ 3351": "M6V",
  "Gl 863.1A": "K5V",
  "GJ 3433": "M4V",
  "GJ 3196A": "M2V",
  "GJ 1155A": "M4V",
  "GJ 3186": "M3.5V",
  "GJ 3183": "dM4.0",
  "GJ 4131": "M4V",
  "GJ 4369": "M3.0V",
  "GJ 4277A": "M2.5V",
  "GJ 3527": "M4V",
  "Gl 52.2": "M2.5V",
  "GJ 1110": "M3.5V",
  "GJ 3794": "M3.5V",
  "GJ 3583": "M2.5V",
  "GJ 3729": "M3V",
  "GJ 3341": "M3.5V",
  "GJ 3397": "DA",
  "GJ 3561": "K9Vk",
  "GJ 3037": "M3.0V",
  "Gl 88": "M4.5V",
  "GJ 3427": "M2.0V",
  "GJ 3797": "DC",
  "GJ 3886": "M4V",
  "GJ 3694": "M3.5V",
  "Gl 7": "M0V",
  "Gl 237": "M0V(k)+M2.5V",
  "GJ 4193": "M3V",
  "GJ 3791": "M4V",
  "GJ 3456": "M3.0V",
  "Gl 181.1": "K7V",
  "GJ 1149": "DA9",
  "GJ 3595": "dM3.5",
  "GJ 3392": "DA8.5",
  "GJ 3105": "dM4.0",
  "GJ 3292": "dM4.0",
  "GJ 4093": "M2.5V",
  "GJ 3646": "M4V",
  "GJ 3744": "M4.5V",
  "GJ 2139": "DA4.9",
  "GJ 3444": "M6V",
  "GJ 9722": "sdM1.5",
  "GJ 3610A": "M4V",
  "GJ 3803A": "DA3.7",
  "GJ 3895": "M4V",
  "GJ 4344": "M2.5V",
  "GJ 3845": "M2V",
  "GJ 4075": "M3.5V",
  "GJ 2097": "M3V",
  "GJ 3272": "M4.5V",
  "GJ 3151A": "M3.0V",
  "GJ 3184": "dM5.0",
  "GJ 3798": "M2.5V",
  "GJ 3681": "M4.5V",
  "GJ 3767": "M1",
  "GJ 4336": "M3V",
  "GJ 3888": "M1.5V",
  "GJ 4028": "dM4.5",
  "GJ 3101": "M3.5V",
  "GJ 4160A": "M5/6",
  "Gl 901": "M0V",
  "GJ 4212": "M3.5V",
  "GJ 4164": "M5V",
  "GJ 3700": "DA5.6",
  "GJ 3477": "M3V",
  "GJ 4178": "M3.5V",
  "GJ 4232": "M4.5V",
  "GJ 3548A": "M3.5",
  "GJ 4072": "DA3.6",
  "GJ 3052": "dM4.0",
  "GJ 3745": "M3.5V",
  "GJ 4302": "M4V",
  "GJ 4191": "DA5.1",
  "GJ 1159A": "M4V",
  "GJ 1201": "DA6.9",
  "Gl 126": "M1V",
  "GJ 3619": "M3.5V",
  "GJ 9141": "M3.5V",
  "GJ 1038": "K7Vk:",
  "GJ 2028": "DA4.7",
  "GJ 3501A": "M0V",
  "GJ 3432": "M4V",
  "GJ 3576": "M5V",
  "GJ 4345": "M5.5V",
  "GJ 3364": "M2.8V",
  "GJ 4381": "M6V",
  "GJ 4029": "M3.5V",
  "GJ 3882": "M1V",
  "GJ 3315": "M3V",
  "GJ 3902": "M5V",
  "GJ 4334": "M3.5V",
  "GJ 4373": "M3V",
  "GJ 4022": "M1.5V",
  "GJ 3947": "M3.5V",
  "GJ 4121": "DA5.5",
  "GJ 4236": "M3V",
  "GJ 3176": "M4V",
  "GJ 3302": "M4.5V",
  "GJ 4371": "M4V",
  "GJ 3698A": "M3.5V",
  "GJ 3113": "M0V",
  "GJ 3934": "M4V",
  "GJ 1141A": "M1.0V",
  "GJ 3439": "DC9",
  "GJ 3216": "M4V",
  "GJ 3529": "dM3.5",
  "GJ 3509": "M1.0V",
  "GJ 9120": "M2.5V",
  "GJ 4364": "M3.0V",
  "Gl 762": "M1V",
  "GJ 3242": "DC",
  "GJ 3453": "M1.5V",
  "Gl 893.1": "M0V",
  "GJ 3536": "M3.5V",
  "GJ 4195": "M4V",
  "GJ 4307": "M2.5V",
  "GJ 3853": "M1V",
  "GJ 3124": "dM4.0",
  "GJ 3510A": "dM4.0",
  "GJ 3381": "M2.5V",
  "GJ 3486": "dM4.0",
  "GJ 3939": "M4V",
  "GJ 3980": "K5V",
  "GJ 4111": "M3.5V",
  "GJ 3235": "M4V",
  "GJ 3910": "dM4.0",
  "GJ 3946": "M2V",
  "GJ 1188": "M3V",
  "GJ 4235": "dM4.0",
  "GJ 3818": "M5V",
  "GJ 3237": "M3.5V",
  "GJ 3268": "M3.5V",
  "GJ 3834": "dM4.5",
  "GJ 4252": "DA5.0",
  "Gl 781.3": "dM3.5",
  "GJ 4187A": "DAH7.3",
  "GJ 3345": "M2.5V",
  "GJ 3889": "M1Vk",
  "GJ 4180": "M3.5V",
  "GJ 2049": "M1.0V",
  "GJ 4059": "M2.5V",
  "GJ 3555": "K7Ve",
  "GJ 3828A": "DA6.6",
  "GJ 9677A": "M4V",
  "GJ 3007": "d/sdM1",
  "GJ 3999A": "M4.5V",
  "GJ 3577A": "M3.5V",
  "GJ 3245": "K4V",
  "GJ 3451": "M3.0V",
  "GJ 3473A": "M2V",
  "GJ 3145": "K7Vk:",
  "GJ 9518": "DA5.8",
  "GJ 3607": "M2.5V",
  "Gl 629.3": "DQ6",
  "GJ 3074": "M1.5V",
  "GJ 4114A": "M2.5V",
  "GJ 3575": "M3.0V",
  "GJ 4011": "M1.1V",
  "GJ 3569": "dM3.5",
  "GJ 3440": "dM5.0",
  "GJ 3624": "M6Ve",
  "GJ 3291": "dM4.0",
  "GJ 3932": "M3.5V",
  "GJ 3825": "usdM1",
  "GJ 3369": "K9Vk:",
  "GJ 4150": "M3.5V",
  "GJ 4051": "M2V",
  "GJ 3736": "M3V",
  "Gl 343": "M1.5V",
  "GJ 4285": "M3.5V",
  "Gl 705.2": "K7V",
  "GJ 4275": "dM4.0",
  "GJ 3928": "M4V",
  "GJ 3935A": "dM6.5",
  "GJ 3720": "M4V",
  "GJ 3342A": "M3V",
  "GJ 3201": "M3V",
  "GJ 3238": "DA8.2",
  "GJ 3688": "M2V",
  "GJ 3565": "dM4.5",
  "Gl 405": "M2V",
  "GJ 3157": "dM2.5",
  "GJ 3641": "M3.5V",
  "GJ 3297": "dM3.5",
  "GJ 3127": "dM4.0",
  "GJ 3168": "M1.5V",
  "GJ 3531": "DA",
  "GJ 9600": "M4V",
  "GJ 2152": "M2.0V",
  "GJ 3554": "dM3.5",
  "GJ 3470": "M2.1V",
  "GJ 3191": "M3.5V",
  "GJ 4125": "M1.5V",
  "GJ 9763": "M3.5V",
  "GJ 3024": "M2V",
  "GJ 3513": "M3.5V",
  "GJ 3914": "K7Vk",
  "GJ 3335": "dM4.5",
  "GJ 9577": "M2.5V",
  "GJ 3402": "M2.5V",
  "Gl 575.1": "M3.5V",
  "GJ 4372": "M3.5V",
  "GJ 3166": "K5V",
  "GJ 4342": "M1.5V",
  "GJ 3640": "M2.0V",
  "GJ 4189A": "M2.5V",
  "GJ 3915": "M2.0V",
  "GJ 3908": "M3.5V",
  "GJ 3515": "M5V",
  "GJ 3234": "M5V",
  "GJ 3613": "M3V",
  "GJ 3143": "dM4.5",
  "GJ 3556": "M2.5V",
  "GJ 3616A": "M2.0V",
  "GJ 4220": "M3.5V",
  "GJ 4263": "M3.5V",
  "GJ 3884": "M5Ve",
  "Gl 540.2": "dM4.5",
  "GJ 4031": "M3V",
  "GJ 3219A": "M3V",
  "GJ 3465": "M3V",
  "GJ 4363": "K6V",
  "Gl 836.4": "sdM2.5",
  "GJ 4025": "DA6.5",
  "GJ 3835": "dM4.0",
  "GJ 1082": "M2.5V",
  "GJ 3673": "dM3.5",
  "GJ 3844": "K7V",
  "GJ 3733": "M3.5V",
  "GJ 3419": "M3V",
  "GJ 9747": "K5V",
  "Gl 85.1": "dM3.0",
  "GJ 3355": "M1.5V",
  "GJ 3658": "M3V",
  "GJ 3799": "M3.0V",
  "GJ 4221": "M4V",
  "GJ 3629": "DA5.2",
  "GJ 4163": "dM4.0",
  "GJ 3819": "M2.5V",
  "GJ 3979": "M1.5V",
  "GJ 3282A": "DC9",
  "GJ 3870": "M2.5V",
  "GJ 4100": "M3V",
  "GJ 3031": "M0.5V",
  "GJ 3026": "dM3.5",
  "GJ 3111": "K4V",
  "GJ 3457A": "M3.0Ve",
  "Gl 167.2": "M4V",
  "GJ 3123": "M4V",
  "GJ 9486": "M3.5V",
  "GJ 3842": "K7V",
  "GJ 3682": "K7V",
  "GJ 3261": "M3.5V"
}